ethlite/Abi.py
ethlite/Account.py
ethlite/CommitedTransaction.py
ethlite/Contracts.py
ethlite/JsonRpc.py
ethlite/NetworkUtil.py
ethlite/Rlp.py
ethlite/Transaction.py
ethlite/Wallet.py
ethlite/__init__.py
ethlite/checkum.py
ethlite/ecdsa/__init__.py
ethlite/ecdsa/_version.py
ethlite/ecdsa/curves.py
ethlite/ecdsa/der.py
ethlite/ecdsa/ecdsa.py
ethlite/ecdsa/ellipticcurve.py
ethlite/ecdsa/keys.py
ethlite/ecdsa/numbertheory.py
ethlite/ecdsa/rfc6979.py
ethlite/ecdsa/six.py
ethlite/ecdsa/util.py
ethlite-0.0.16.dist-info/LICENSE
ethlite-0.0.16.dist-info/METADATA
ethlite-0.0.16.dist-info/WHEEL
ethlite-0.0.16.dist-info/top_level.txt
ethlite-0.0.16.dist-info/RECORD
