Metadata-Version: 2.1
Name: ethlite
Version: 0.0.16
Summary: A tiny web3/python alternative to interact with any ethereum compatible blockchain
Home-page: https://github.com/emilianobilli/ethlite
Author: Emiliano A. Billi
Author-email: emiliano.billi@gmail.com
License: UNKNOWN
Platform: UNKNOWN
Classifier: Programming Language :: Python :: 3
Classifier: License :: OSI Approved :: MIT License
Classifier: Operating System :: OS Independent
Requires-Python: >=3.5
Requires-Dist: pysha3
Requires-Dist: requests
Requires-Dist: six
